agesuta/__init__.py
agesuta/com.py
agesuta/configmanager.py
agesuta/date.txt
agesuta/slackapi.py
agesuta/version.txt
agesuta-0.1.17.dist-info/LICENSE
agesuta-0.1.17.dist-info/METADATA
agesuta-0.1.17.dist-info/WHEEL
agesuta-0.1.17.dist-info/top_level.txt
agesuta-0.1.17.dist-info/RECORD
