Metadata-Version: 2.1
Name: agesuta
Version: 0.1.17
Summary: A custom logging utility and other utilities with Rich console output, file handling, Slack notification, etc.
Home-page: https://github.com/AgemameSutachi/agesuta
Author: AgemameSutachi
Author-email: sutachiagemame@gmail.com
License: MIT
Keywords: logging custom logger rich file rotation slack requests utility
Classifier: Development Status :: 3 - Alpha
Classifier: Intended Audience :: Developers
Classifier: Topic :: Software Development :: Libraries :: Python Modules
Classifier: Topic :: System :: Logging
Classifier: Topic :: Communications :: Chat
Classifier: License :: OSI Approved :: MIT License
Classifier: Programming Language :: Python :: 3
Classifier: Programming Language :: Python :: 3.6
Classifier: Programming Language :: Python :: 3.7
Classifier: Programming Language :: Python :: 3.8
Classifier: Programming Language :: Python :: 3.9
Classifier: Programming Language :: Python :: 3.10
Classifier: Programming Language :: Python :: 3.11
Classifier: Programming Language :: Python :: 3.12
Requires-Python: >=3.6
License-File: LICENSE
Requires-Dist: certifi>=2025.4.26
Requires-Dist: chardet>=5.2.0
Requires-Dist: charset-normalizer>=3.4.2
Requires-Dist: idna>=3.10
Requires-Dist: markdown-it-py>=3.0.0
Requires-Dist: mdurl>=0.1.2
Requires-Dist: Pygments>=2.19.1
Requires-Dist: requests>=2.32.3
Requires-Dist: rich>=14.0.0
Requires-Dist: slack-sdk>=3.35.0
Requires-Dist: urllib3>=2.4.0
